{"arrivalTime":540,"destination":"Bromley-By-Bow","times":[{"station":"Russell Square","time":522},{"station":"Ealing Common","time":501},{"station":"West India Quay","time":527},{"station":"Turnham Green","time":507},{"station":"Euston Square","time":519},{"station":"Northwood","time":498},{"station":"Shadwell","time":527},{"station":"Stepney Green","time":534},{"station":"Morden","time":498},{"station":"White City","time":510},{"station":"Warren Street","time":522},{"station":"Greenford","time":498},{"station":"Old Street","time":522},{"station":"Hainault","time":516},{"station":"South Wimbledon","time":500},{"station":"Wood Green Station","time":507},{"station":"Deptford Bridge","time":512},{"station":"Goodge Street","time":522},{"station":"Blackwall","time":533},{"station":"Baker Street","time":520},{"station":"Kingsbury","time":514},{"station":"Ruislip Gardens","time":492},{"station":"Canons Park","time":509},{"station":"Southgate","time":498},{"station":"Green Park","time":522},{"station":"Watford Underground Station","time":488},{"station":"Hornchurch","time":513},{"station":"Dagenham East","time":519},{"station":"Cyprus","time":527},{"station":"Plaistow","time":537},{"station":"Cockfosters","time":493},{"station":"Chorleywood","time":487},{"station":"Embankment","time":520},{"station":"Barbican","time":526},{"station":"Limehouse","time":527},{"station":"Osterley","time":491},{"station":"Goldhawk Road","time":504},{"station":"Uxbridge","time":489},{"station":"Crossharbour","time":520},{"station":"Camden Town","time":520},{"station":"Notting Hill Gate","time":516},{"station":"All Saints","time":530},{"station":"Kew Gardens","time":497},{"station":"Mansion House","time":524},{"station":"Preston Road","time":513},{"station":"Brixton","time":516},{"station":"Woodford","time":526},{"station":"Amersham","time":480},{"station":"Ruislip Manor","time":499},{"station":"West Acton","time":503},{"station":"East Ham","time":532},{"station":"Beckton","time":523},{"station":"Barking","time":529},{"station":"Stratford High Street","time":531},{"station":"Willesden Green","time":512},{"station":"East Acton","time":508},{"station":"St. Paul\u0027s","time":527},{"station":"Great Portland Street","time":518},{"station":"Heathrow Terminal 4","time":467},{"station":"Tottenham Court Road","time":524},{"station":"Borough Station","time":525},{"station":"Devons Road","time":532},{"station":"Sloane Square","time":516},{"station":"Stanmore","time":507},{"station":"Bond Street","time":523},{"station":"Ruislip","time":497},{"station":"Golders Green","time":507},{"station":"Chigwell","time":515},{"station":"Oxford Circus","time":523},{"station":"Maida Vale","time":512},{"station":"Upton Park","time":536},{"station":"Lancaster Gate","time":519},{"station":"Marble Arch","time":520},{"station":"Abbey Road DLR Station","time":533},{"station":"Pontoon Dock","time":531},{"station":"Edgware","time":494},{"station":"Wembley Park","time":515},{"station":"Brent Cross Station","time":505},{"station":"Turnpike Lane","time":509},{"station":"Lewisham","time":508},{"station":"Barons Court","time":512},{"station":"Snaresbrook","time":531},{"station":"Langdon Park","time":531},{"station":"St James\u0027s Park","time":521},{"station":"Hillingdon","time":492},{"station":"Ickenham","time":495},{"station":"Boston Manor","time":494},{"station":"Greenwich Station","time":515},{"station":"South Kensington","time":517},{"station":"Canada Water","time":531},{"station":"West Ruislip","time":489},{"station":"Pudding Mill Lane","time":534},{"station":"Upney","time":526},{"station":"Shepherd\u0027s Bush Market","time":505},{"station":"Beckton Park","time":529},{"station":"Hounslow West","time":484},{"station":"Hammersmith","time":510},{"station":"West Harrow","time":505},{"station":"Wimbledon","time":493},{"station":"Edgware Road","time":517},{"station":"London City Airport","time":529},{"station":"Vauxhall","time":516},{"station":"Oakwood","time":495},{"station":"Stamford Brook","time":507},{"station":"Charing Cross","time":524},{"station":"Highbury \u0026 Islington","time":518},{"station":"Canning Town","time":537},{"station":"Tottenham Hale","time":511},{"station":"Upminster Bridge","time":511},{"station":"Gants Hill","time":524},{"station":"Chalfont \u0026 Latimer","time":483},{"station":"Kensal Green","time":506},{"station":"Elephant \u0026 Castle","time":523},{"station":"East Putney","time":500},{"station":"Southfields","time":498},{"station":"Loughton","time":520},{"station":"Burnt Oak","time":497},{"station":"Clapham North","time":515},{"station":"Eastcote","time":501},{"station":"Bounds Green","time":506},{"station":"Covent Garden","time":522},{"station":"Arnos Grove","time":501},{"station":"Pinner","time":503},{"station":"Oval","time":519},{"station":"Ealing Broadway","time":501},{"station":"Neasden","time":513},{"station":"Tower Hill","time":527},{"station":"Temple","time":520},{"station":"Sudbury Town","time":492},{"station":"Belsize Park","time":515},{"station":"Leicester Square","time":522},{"station":"Arsenal","time":517},{"station":"Bethnal Green","time":533},{"station":"Kilburn Park","time":511},{"station":"High Barnet","time":493},{"station":"Bow Church DLR","time":533},{"station":"Queensway","time":517},{"station":"Tower Gateway","time":523},{"station":"Prince Regent","time":532},{"station":"Wembley Central","time":492},{"station":"Custom House","time":535},{"station":"Northolt","time":495},{"station":"Gallions Reach","time":525},{"station":"Mornington Crescent","time":519},{"station":"South Woodford","time":529},{"station":"Canary Wharf","time":533},{"station":"Westbourne Park","time":511},{"station":"Paddington (H\u0026C Line)","time":515},{"station":"Finchley Road","time":517},{"station":"Hendon Central","time":502},{"station":"Heron Quays","time":523},{"station":"Bromley-By-Bow","time":540},{"station":"Tooting Broadway","time":505},{"station":"Hampstead Station","time":510},{"station":"Stratford","time":536},{"station":"Elm Park","time":516},{"station":"Heathrow Terminals 1-3","time":478},{"station":"Elverson Road","time":510},{"station":"Parsons Green","time":506},{"station":"Tufnell Park","time":516},{"station":"Pimlico","time":517},{"station":"Latimer Road","time":508},{"station":"Finsbury Park","time":516},{"station":"Northwood Hills","time":501},{"station":"Colliers Wood","time":503},{"station":"Royal Victoria","time":536},{"station":"Richmond","time":494},{"station":"Perivale","time":500},{"station":"Barkingside","time":520},{"station":"South Kenton","time":488},{"station":"Holland Park","time":514},{"station":"Victoria","time":519},{"station":"Totteridge \u0026 Whetstone","time":496},{"station":"Northfields","time":499},{"station":"Heathrow Terminal 5","time":474},{"station":"Marylebone","time":518},{"station":"Seven Sisters","time":514},{"station":"Cannon Street","time":526},{"station":"Kennington Station","time":522},{"station":"Redbridge","time":528},{"station":"Tooting Bec Station","time":507},{"station":"Chalk Farm","time":518},{"station":"St.John\u0027s Wood","time":519},{"station":"Woolwich Arsenal DLR","time":521},{"station":"North Wembley","time":490},{"station":"Rayners Lane","time":503},{"station":"Monument","time":526},{"station":"Royal Albert","time":530},{"station":"Wood Lane","time":507},{"station":"Clapham South","time":511},{"station":"Woodside Park","time":500},{"station":"Queensbury","time":512},{"station":"Gloucester Road","time":516},{"station":"Shepherd\u0027s Bush (Central Line)","time":512},{"station":"Theydon Bois","time":513},{"station":"Angel","time":520},{"station":"Rickmansworth","time":490},{"station":"Moor Park","time":494},{"station":"North Ealing","time":499},{"station":"Kenton","time":485},{"station":"Piccadilly Circus","time":523},{"station":"East India","time":535},{"station":"Newbury Park","time":522},{"station":"Knightsbridge","time":519},{"station":"Kilburn","time":514},{"station":"Euston","time":521},{"station":"Colindale","time":499},{"station":"Ladbroke Grove","time":510},{"station":"Holloway Road","time":518},{"station":"Sudbury Hill","time":494},{"station":"Epping","time":510},{"station":"Croxley","time":491},{"station":"East Finchley","time":507},{"station":"Wanstead","time":530},{"station":"Canary Wharf DLR Station","time":526},{"station":"Finchley Central","time":504},{"station":"Bow Road","time":538},{"station":"Fulham Broadway","time":508},{"station":"West Finchley","time":502},{"station":"Alperton","time":495},{"station":"Archway","time":514},{"station":"Waterloo","time":525},{"station":"South Quay","time":522},{"station":"Blackfriars","time":522},{"station":"South Ruislip","time":494},{"station":"Northwick Park","time":510},{"station":"Dagenham Heathway","time":522},{"station":"Hyde Park Corner","time":521},{"station":"West Hampstead","time":516},{"station":"Island Gardens","time":517},{"station":"Clapham Common","time":513},{"station":"North Greenwich","time":536},{"station":"Bayswater","time":514},{"station":"Wimbledon Park","time":495},{"station":"Ravenscourt Park","time":508},{"station":"Grange Hill","time":513},{"station":"Swiss Cottage","time":518},{"station":"Paddington","time":515},{"station":"Roding Valley","time":518},{"station":"Aldgate","time":527},{"station":"Poplar","time":531},{"station":"Chancery Lane","time":526},{"station":"Walthamstow Central","time":507},{"station":"Leyton","time":534},{"station":"Royal Oak","time":513},{"station":"Willesden Junction","time":503},{"station":"Earl\u0027s Court","time":514},{"station":"King George V.","time":525},{"station":"Debden","time":515},{"station":"Park Royal","time":497},{"station":"Aldgate East","time":529},{"station":"Bermondsey","time":528},{"station":"Hounslow Central","time":488},{"station":"South Ealing","time":502},{"station":"Putney Bridge","time":503},{"station":"Harrow \u0026 Wealdstone Station","time":482},{"station":"Bank","time":529},{"station":"West Ham","time":539},{"station":"Westferry","time":529},{"station":"Harlesden","time":501},{"station":"Fairlop","time":518},{"station":"Mile End","time":536},{"station":"North Harrow","time":506},{"station":"Hanger Lane","time":502},{"station":"Leytonstone","time":532},{"station":"West Silvertown DLR Station","time":533},{"station":"Liverpool Street","time":531},{"station":"Hammersmith (Ham \u0026 City Line)","time":502},{"station":"Gunnersbury","time":501},{"station":"Highgate","time":511},{"station":"Farringdon","time":523},{"station":"Mudchute","time":519},{"station":"Whitechapel","time":532},{"station":"Queen\u0027s Park","time":510},{"station":"Star Lane","time":536},{"station":"Stratford International DLR","time":526},{"station":"Holborn","time":524},{"station":"Becontree","time":523},{"station":"Stockwell","time":517},{"station":"Caledonian Road","time":519},{"station":"Acton Town","time":504},{"station":"Hatton Cross","time":482},{"station":"Dollis Hill","time":512},{"station":"Mill Hill East","time":500},{"station":"North Acton","time":505},{"station":"West Brompton","time":510},{"station":"Lambeth North","time":523},{"station":"Southwark","time":525},{"station":"Upminster","time":509},{"station":"Kensington (Olympia)","time":499},{"station":"London Bridge Station","time":527},{"station":"Regent\u0027s Park","time":521},{"station":"Hounslow East","time":490},{"station":"Blackhorse Road","time":509},{"station":"West Kensington","time":513},{"station":"Cutty Sark","time":516},{"station":"Warwick Avenue","time":513},{"station":"Buckhurst Hill","time":523},{"station":"Chiswick Park","time":503},{"station":"Manor House","time":511},{"station":"Harrow-on-the-Hill","time":509},{"station":"Balham","time":509},{"station":"High Street Kensington","time":514},{"station":"King\u0027s Cross St.Pancras","time":520},{"station":"Moorgate","time":528},{"station":"Kentish Town","time":517},{"station":"Westminster","time":523},{"station":"Stonebridge Park","time":499},{"station":"South Harrow","time":497},{"station":"Chesham","time":458}]}