{"arrivalTime":180,"destination":"Southfields","times":[{"station":"Tooting Bec Station","time":-50},{"station":"Sudbury Hill","time":-44},{"station":"Elephant \u0026 Castle","time":-37},{"station":"Hammersmith (Ham \u0026 City Line)","time":-60},{"station":"Ealing Broadway","time":-39},{"station":"St James\u0027s Park","time":-31},{"station":"Kew Gardens","time":-25},{"station":"Clapham North","time":-41},{"station":"Stratford","time":-54},{"station":"Bayswater","time":-36},{"station":"Bank","time":-44},{"station":"Gunnersbury","time":-21},{"station":"Earl\u0027s Court","time":-7},{"station":"South Wimbledon","time":-56},{"station":"Westminster","time":-32},{"station":"Gloucester Road","time":-23},{"station":"Wood Lane","time":-55},{"station":"Euston","time":-57},{"station":"Notting Hill Gate","time":-34},{"station":"Clapham South","time":-46},{"station":"Mansion House","time":-39},{"station":"Lambeth North","time":-35},{"station":"Monument","time":-41},{"station":"South Kensington","time":-25},{"station":"Turnham Green","time":-19},{"station":"Edgware Road","time":-40},{"station":"Sudbury Town","time":-42},{"station":"Cannon Street","time":-40},{"station":"London Bridge Station","time":-37},{"station":"South Ealing","time":-35},{"station":"Marylebone","time":-43},{"station":"Balham","time":-48},{"station":"Paddington (H\u0026C Line)","time":-47},{"station":"Kennington Station","time":-35},{"station":"Fulham Broadway","time":-4},{"station":"King\u0027s Cross St.Pancras","time":-59},{"station":"Putney Bridge","time":1},{"station":"Richmond","time":-28},{"station":"Southwark","time":-35},{"station":"Morden","time":-59},{"station":"Goldhawk Road","time":-58},{"station":"West Ham","time":-51},{"station":"Northfields","time":-38},{"station":"High Street Kensington","time":-11},{"station":"Blackfriars","time":-37},{"station":"Ravenscourt Park","time":-14},{"station":"Canada Water","time":-42},{"station":"Wimbledon Park","time":-7},{"station":"Clapham Common","time":-44},{"station":"Latimer Road","time":-54},{"station":"Brixton","time":-38},{"station":"West Brompton","time":-5},{"station":"Parsons Green","time":-2},{"station":"Ealing Common","time":-34},{"station":"Hounslow West","time":-51},{"station":"Tower Hill","time":-43},{"station":"Pimlico","time":-33},{"station":"Oxford Circus","time":-46},{"station":"Warren Street","time":-56},{"station":"Green Park","time":-48},{"station":"Westbourne Park","time":-51},{"station":"Victoria","time":-30},{"station":"Heathrow Terminals 1-3","time":-57},{"station":"Regent\u0027s Park","time":-47},{"station":"Heathrow Terminal 5","time":-60},{"station":"Barons Court","time":-10},{"station":"Colliers Wood","time":-54},{"station":"West Kensington","time":-8},{"station":"Maida Vale","time":-48},{"station":"Stamford Brook","time":-15},{"station":"Canary Wharf","time":-45},{"station":"Baker Street","time":-45},{"station":"Waterloo","time":-33},{"station":"Hounslow East","time":-45},{"station":"Park Royal","time":-38},{"station":"Queen\u0027s Park","time":-50},{"station":"Kilburn Park","time":-49},{"station":"Temple","time":-36},{"station":"Canning Town","time":-48},{"station":"Wimbledon","time":-9},{"station":"Ladbroke Grove","time":-52},{"station":"Charing Cross","time":-41},{"station":"Warwick Avenue","time":-45},{"station":"North Ealing","time":-36},{"station":"Hammersmith","time":-12},{"station":"Boston Manor","time":-42},{"station":"Oval","time":-38},{"station":"Paddington","time":-38},{"station":"Alperton","time":-40},{"station":"Stockwell","time":-36},{"station":"North Greenwich","time":-46},{"station":"Royal Oak","time":-49},{"station":"Hatton Cross","time":-55},{"station":"Chiswick Park","time":-29},{"station":"South Harrow","time":-48},{"station":"East Putney","time":4},{"station":"Bermondsey","time":-39},{"station":"Shepherd\u0027s Bush Market","time":-57},{"station":"Sloane Square","time":-27},{"station":"Southfields","time":180},{"station":"Embankment","time":-35},{"station":"Tooting Broadway","time":-52},{"station":"Hounslow Central","time":-48},{"station":"Piccadilly Circus","time":-44},{"station":"Osterley","time":-43},{"station":"Rayners Lane","time":-51},{"station":"Vauxhall","time":-34},{"station":"Acton Town","time":-32}]}