{"arrivalTime":960,"destination":"North Wembley","times":[{"station":"Leyton","time":908},{"station":"Walthamstow Central","time":907},{"station":"Croxley","time":891},{"station":"Bethnal Green","time":914},{"station":"Kingsbury","time":919},{"station":"Debden","time":887},{"station":"Canons Park","time":913},{"station":"Wembley Central","time":952},{"station":"Acton Town","time":904},{"station":"St James\u0027s Park","time":920},{"station":"Ruislip Manor","time":904},{"station":"Wanstead","time":902},{"station":"Caledonian Road","time":922},{"station":"North Ealing","time":895},{"station":"Monument","time":913},{"station":"Willesden Green","time":917},{"station":"Langdon Park","time":907},{"station":"Farringdon","time":922},{"station":"North Greenwich","time":911},{"station":"Elephant \u0026 Castle","time":916},{"station":"East Putney","time":905},{"station":"Loughton","time":893},{"station":"Dagenham East","time":887},{"station":"Embankment","time":920},{"station":"Knightsbridge","time":919},{"station":"Heathrow Terminal 4","time":867},{"station":"Harrow \u0026 Wealdstone Station","time":952},{"station":"Clapham Common","time":911},{"station":"Finchley Road","time":922},{"station":"All Saints","time":908},{"station":"Limehouse","time":914},{"station":"Blackfriars","time":917},{"station":"Shepherd\u0027s Bush Market","time":919},{"station":"Marble Arch","time":923},{"station":"Poplar","time":910},{"station":"Angel","time":920},{"station":"Goodge Street","time":920},{"station":"Marylebone","time":929},{"station":"Bank","time":918},{"station":"Moor Park","time":894},{"station":"Victoria","time":921},{"station":"Hatton Cross","time":882},{"station":"Colliers Wood","time":900},{"station":"Bounds Green","time":909},{"station":"Euston Square","time":925},{"station":"Queensbury","time":916},{"station":"Ruislip Gardens","time":901},{"station":"Fairlop","time":893},{"station":"London Bridge Station","time":917},{"station":"Royal Oak","time":926},{"station":"Kensal Green","time":942},{"station":"Heathrow Terminals 1-3","time":878},{"station":"Custom House","time":906},{"station":"Kenton","time":955},{"station":"South Kenton","time":958},{"station":"Cockfosters","time":896},{"station":"Watford Underground Station","time":888},{"station":"Edgware","time":892},{"station":"West Ham","time":908},{"station":"Borough Station","time":914},{"station":"Colindale","time":897},{"station":"Sudbury Hill","time":903},{"station":"Belsize Park","time":913},{"station":"Elverson Road","time":892},{"station":"Dollis Hill","time":917},{"station":"Gunnersbury","time":903},{"station":"Stanmore","time":911},{"station":"Whitechapel","time":908},{"station":"Stockwell","time":916},{"station":"Chigwell","time":893},{"station":"Northwood","time":898},{"station":"East Finchley","time":906},{"station":"Hyde Park Corner","time":921},{"station":"Westferry","time":912},{"station":"Chesham","time":866},{"station":"Amersham","time":857},{"station":"Tower Hill","time":912},{"station":"Roding Valley","time":895},{"station":"Chalk Farm","time":916},{"station":"Redbridge","time":900},{"station":"Arsenal","time":920},{"station":"South Ealing","time":902},{"station":"Warwick Avenue","time":933},{"station":"Holloway Road","time":921},{"station":"Cyprus","time":901},{"station":"Hillingdon","time":896},{"station":"Star Lane","time":906},{"station":"Latimer Road","time":922},{"station":"West Hampstead","time":921},{"station":"Greenwich Station","time":895},{"station":"East India","time":908},{"station":"Epping","time":882},{"station":"Finsbury Park","time":918},{"station":"High Street Kensington","time":923},{"station":"West Silvertown DLR Station","time":905},{"station":"Aldgate East","time":910},{"station":"Canary Wharf DLR Station","time":908},{"station":"West Finchley","time":901},{"station":"Gloucester Road","time":922},{"station":"Tottenham Court Road","time":923},{"station":"Mill Hill East","time":896},{"station":"Ravenscourt Park","time":910},{"station":"Beckton Park","time":902},{"station":"Kew Gardens","time":899},{"station":"Hendon Central","time":900},{"station":"Barons Court","time":914},{"station":"Burnt Oak","time":894},{"station":"Newbury Park","time":895},{"station":"Tufnell Park","time":916},{"station":"Finchley Central","time":903},{"station":"Dagenham Heathway","time":890},{"station":"Northwick Park","time":915},{"station":"Elm Park","time":884},{"station":"Chancery Lane","time":920},{"station":"Pudding Mill Lane","time":906},{"station":"Royal Victoria","time":908},{"station":"Tooting Bec Station","time":906},{"station":"Bromley-By-Bow","time":908},{"station":"Putney Bridge","time":908},{"station":"Oxford Circus","time":924},{"station":"King George V.","time":897},{"station":"Regent\u0027s Park","time":925},{"station":"Northfields","time":899},{"station":"West India Quay","time":910},{"station":"Willesden Junction","time":945},{"station":"Theydon Bois","time":885},{"station":"Baker Street","time":927},{"station":"Tottenham Hale","time":913},{"station":"Plaistow","time":905},{"station":"Oval","time":916},{"station":"Old Street","time":919},{"station":"North Harrow","time":906},{"station":"Neasden","time":919},{"station":"Upminster","time":877},{"station":"Queen\u0027s Park","time":939},{"station":"Grange Hill","time":891},{"station":"Uxbridge","time":893},{"station":"Turnham Green","time":907},{"station":"Clapham South","time":910},{"station":"Park Royal","time":896},{"station":"South Harrow","time":905},{"station":"Bond Street","time":925},{"station":"Buckhurst Hill","time":896},{"station":"Warren Street","time":922},{"station":"Upminster Bridge","time":879},{"station":"Pinner","time":903},{"station":"Wembley Park","time":920},{"station":"Crossharbour","time":902},{"station":"Becontree","time":891},{"station":"Wood Lane","time":920},{"station":"Lancaster Gate","time":922},{"station":"Prince Regent","time":905},{"station":"Holborn","time":922},{"station":"Brent Cross Station","time":903},{"station":"Mansion House","time":916},{"station":"Russell Square","time":922},{"station":"Hornchurch","time":881},{"station":"Stamford Brook","time":909},{"station":"High Barnet","time":891},{"station":"Heathrow Terminal 5","time":874},{"station":"West Harrow","time":910},{"station":"Barbican","time":920},{"station":"Southfields","time":903},{"station":"Abbey Road DLR Station","time":903},{"station":"Brixton","time":914},{"station":"Hounslow East","time":890},{"station":"Stepney Green","time":909},{"station":"Westbourne Park","time":925},{"station":"Rickmansworth","time":887},{"station":"Beckton","time":896},{"station":"Chiswick Park","time":900},{"station":"Charing Cross","time":923},{"station":"Rayners Lane","time":908},{"station":"Vauxhall","time":918},{"station":"Sloane Square","time":919},{"station":"White City","time":919},{"station":"Kentish Town","time":917},{"station":"Wimbledon","time":898},{"station":"Green Park","time":923},{"station":"Ealing Common","time":905},{"station":"Kilburn","time":919},{"station":"Cutty Sark","time":897},{"station":"Clapham North","time":913},{"station":"Seven Sisters","time":915},{"station":"Moorgate","time":918},{"station":"Canning Town","time":909},{"station":"Liverpool Street","time":916},{"station":"Lambeth North","time":918},{"station":"Mornington Crescent","time":920},{"station":"Tooting Broadway","time":903},{"station":"Goldhawk Road","time":917},{"station":"East Ham","time":901},{"station":"Bermondsey","time":916},{"station":"Upton Park","time":904},{"station":"Canary Wharf","time":913},{"station":"Paddington","time":931},{"station":"Harlesden","time":948},{"station":"Balham","time":908},{"station":"Greenford","time":908},{"station":"West Brompton","time":915},{"station":"Stratford International DLR","time":905},{"station":"Bow Church DLR","time":905},{"station":"Waterloo","time":921},{"station":"Hanger Lane","time":913},{"station":"Kilburn Park","time":936},{"station":"Woolwich Arsenal DLR","time":893},{"station":"Southgate","time":901},{"station":"North Wembley","time":960},{"station":"London City Airport","time":901},{"station":"South Kensington","time":920},{"station":"Mile End","time":911},{"station":"West Ruislip","time":898},{"station":"Harrow-on-the-Hill","time":914},{"station":"Archway","time":912},{"station":"Cannon Street","time":914},{"station":"North Acton","time":915},{"station":"Hounslow West","time":884},{"station":"Royal Albert","time":904},{"station":"Preston Road","time":918},{"station":"Stratford","time":909},{"station":"Fulham Broadway","time":913},{"station":"St. Paul\u0027s","time":918},{"station":"Euston","time":922},{"station":"Woodford","time":899},{"station":"Temple","time":918},{"station":"Heron Quays","time":907},{"station":"Turnpike Lane","time":913},{"station":"Richmond","time":896},{"station":"Hampstead Station","time":908},{"station":"Perivale","time":911},{"station":"Holland Park","time":925},{"station":"Blackhorse Road","time":910},{"station":"Canada Water","time":914},{"station":"Sudbury Town","time":900},{"station":"Mudchute","time":901},{"station":"Kennington Station","time":919},{"station":"Northolt","time":906},{"station":"Pimlico","time":920},{"station":"St.John\u0027s Wood","time":925},{"station":"Island Gardens","time":900},{"station":"Camden Town","time":919},{"station":"Bayswater","time":928},{"station":"Northwood Hills","time":901},{"station":"Aldgate","time":913},{"station":"Arnos Grove","time":904},{"station":"West Acton","time":912},{"station":"Golders Green","time":906},{"station":"Chalfont \u0026 Latimer","time":875},{"station":"Wimbledon Park","time":900},{"station":"Shepherd\u0027s Bush (Central Line)","time":923},{"station":"Hounslow Central","time":888},{"station":"Boston Manor","time":894},{"station":"Notting Hill Gate","time":926},{"station":"Osterley","time":891},{"station":"Pontoon Dock","time":903},{"station":"Piccadilly Circus","time":923},{"station":"Morden","time":896},{"station":"Manor House","time":915},{"station":"Kensington (Olympia)","time":899},{"station":"Lewisham","time":891},{"station":"Devons Road","time":905},{"station":"King\u0027s Cross St.Pancras","time":923},{"station":"Upney","time":894},{"station":"Highgate","time":909},{"station":"Woodside Park","time":898},{"station":"Stonebridge Park","time":949},{"station":"Edgware Road","time":930},{"station":"Tower Gateway","time":908},{"station":"Eastcote","time":905},{"station":"Oakwood","time":898},{"station":"Barkingside","time":894},{"station":"Swiss Cottage","time":923},{"station":"Queensway","time":924},{"station":"Chorleywood","time":884},{"station":"Hammersmith (Ham \u0026 City Line)","time":916},{"station":"South Ruislip","time":903},{"station":"Westminster","time":922},{"station":"Hammersmith","time":912},{"station":"South Wimbledon","time":898},{"station":"Covent Garden","time":922},{"station":"Leicester Square","time":923},{"station":"Leytonstone","time":906},{"station":"Totteridge \u0026 Whetstone","time":894},{"station":"Paddington (H\u0026C Line)","time":927},{"station":"Ruislip","time":902},{"station":"Parsons Green","time":911},{"station":"Shadwell","time":916},{"station":"Alperton","time":898},{"station":"Stratford High Street","time":901},{"station":"Snaresbrook","time":903},{"station":"South Quay","time":905},{"station":"Wood Green Station","time":910},{"station":"South Woodford","time":901},{"station":"Maida Vale","time":934},{"station":"Southwark","time":919},{"station":"West Kensington","time":916},{"station":"Deptford Bridge","time":893},{"station":"Gallions Reach","time":898},{"station":"Barking","time":898},{"station":"East Acton","time":917},{"station":"Bow Road","time":909},{"station":"Blackwall","time":909},{"station":"Highbury \u0026 Islington","time":920},{"station":"Earl\u0027s Court","time":918},{"station":"Ladbroke Grove","time":923},{"station":"Ealing Broadway","time":909},{"station":"Gants Hill","time":897},{"station":"Great Portland Street","time":926},{"station":"Hainault","time":891},{"station":"Ickenham","time":899}]}